[{"username":"@suin(Craftsman Software)","avatar":"https://qiita-image-store.s3.amazonaws.com/0/889/profile-images/1473682133","datetime":"2022-03-31T00:00:00Z","title":"エープリルフールなのでJavaScriptの信じがたい話をします","url":"https://qiita.com/suin/items/461c096bef318a259c80","tags":["JavaScript","TypeScript"],"lgtm":325},{"username":"@choo","avatar":"https://qiita-image-store.s3.ap-northeast-1.amazonaws.com/0/138646/profile-images/1577629276","datetime":"2022-04-03T00:00:00Z","title":"【個人開発】爆速な賃貸物件の検索サービスを作った","url":"https://qiita.com/choo/items/2efacb2f94f6c9c46417","tags":["Python","JavaScript","gcp","React","個人開発"],"lgtm":53},{"username":"@kaedeee","avatar":"https://s3-ap-northeast-1.amazonaws.com/qiita-image-store/0/1900756/6949fe9bd24921ca10055cbb1fa1f53f435f022d/x_large.png?1644325731","datetime":"2022-04-02T00:00:00Z","title":"九州大学の非公式アプリを一カ月で作ってみた。","url":"https://qiita.com/kaedeee/items/d573d85c9d52eb82e841","tags":["Android","iOS","大学生","Flutter","コロナウイルス"],"lgtm":35},{"username":"@hrfmjp","avatar":"https://qiita-image-store.s3.ap-northeast-1.amazonaws.com/0/167110/profile-images/1586403409","datetime":"2022-04-01T00:00:00Z","title":"Microsoft Teams メンションの「さん付け問題」に終止符を打つ！「僕が実践する最強のメンションさん付けポリシー」","url":"https://qiita.com/hrfmjp/items/f99b8ca0a792211416cc","tags":["MicrosoftTeams"],"lgtm":30},{"username":"@zrn-ns(株式会社with)","avatar":"https://qiita-image-store.s3.ap-northeast-1.amazonaws.com/0/95499/profile-images/1606344641","datetime":"2022-04-01T00:00:00Z","title":"【Xcode】iOSエンジニアが真っ先に設定すべきXcode設定集","url":"https://qiita.com/zrn-ns/items/8493413e55b7329c023a","tags":["Xcode","iOS","Swift","駆け出しエンジニア"],"lgtm":27},{"username":"@u2dayo","avatar":"https://s3-ap-northeast-1.amazonaws.com/qiita-image-store/0/595910/b1d4e466d8b449f49315e2d636d8ddafc1fab61a/large.png?1587467337","datetime":"2022-04-03T00:00:00Z","title":"【AtCoder解説】PythonでABC246のA,B,C,D,E,F問題を制する！","url":"https://qiita.com/u2dayo/items/4896cea07b59c707df3a","tags":["Python","AtCoder","Python3","競技プログラミング","AtCoderBeginnerContest"],"lgtm":12},{"username":"@kaku3","avatar":"https://qiita-image-store.s3.amazonaws.com/0/136165/profile-images/1473719863","datetime":"2022-04-02T00:00:00Z","title":"新卒エンジニアが最初に学ぶとよいことは…","url":"https://qiita.com/kaku3/items/fb949aa1a53f1f71c796","tags":["ポエム","新人教育","新人プログラマ応援"],"lgtm":13},{"username":"@neon-izm","avatar":"https://qiita-image-store.s3.amazonaws.com/0/40627/profile-images/1473688501","datetime":"2022-04-01T00:00:00Z","title":"Unityで「ここは自由文言で20文字が入力できる」と言われた時に考えることの全て","url":"https://qiita.com/neon-izm/items/307b5adedaac73a0bcd0","tags":["Unity"],"lgtm":82},{"username":"@okaponta_","avatar":"https://avatars3.githubusercontent.com/u/59508678?v=4","datetime":"2022-04-03T00:00:00Z","title":"【色変記事】転職を機に一度やめた競プロを復帰して水色になれました","url":"https://qiita.com/okaponta_/items/95edd5dd312087da28d8","tags":["Rust","AtCoder","ポエム","競技プログラミング"],"lgtm":11},{"username":"@SnykSec(Snyk株式会社)","avatar":"https://s3-ap-northeast-1.amazonaws.com/qiita-image-store/0/2216557/f8f98fbbe538117d38c7a48dd136ae0176e06977/x_large.png?1635293588","datetime":"2022-04-01T00:00:00Z","title":"Spring4Shell：JavaのSpringフレームワークのゼロデイRCE脆弱性について解説します","url":"https://qiita.com/SnykSec/items/e612511db7adc4537ab9","tags":["Java","spring","セキュリティ","脆弱性","Snyk"],"lgtm":12},{"username":"@Varnet","avatar":"https://pbs.twimg.com/profile_images/1400407390365777925/6l5JI1-j_bigger.jpg","datetime":"2022-04-02T00:00:00Z","title":"物体検出・ファインチューニングで書籍冊数認識アプリケーション開発","url":"https://qiita.com/Varnet/items/3765a4e342c389a493c0","tags":["Python","機械学習","画像認識","物体検出","ファインチューニング"],"lgtm":8},{"username":"@2san(株式会社マイスター・ギルド)","avatar":"https://qiita-image-store.s3.ap-northeast-1.amazonaws.com/0/973482/profile-images/1633441669","datetime":"2022-04-01T00:00:00Z","title":"Golangのポインタで詰まったので備忘録","url":"https://qiita.com/2san/items/0faa3939d55f8594393a","tags":["Go"],"lgtm":17},{"username":"@sugulu_Ogawa_ISID(電通国際情報サービス（ISID）)","avatar":"https://s3-ap-northeast-1.amazonaws.com/qiita-image-store/0/191401/185398f529f8156fed141d7b2e1b0a78fc114172/large.png?1599774000","datetime":"2022-04-03T00:00:00Z","title":"GitHub Copilotの使用方法：Python、PyTorchを少しだけ実装してみた動画解説記事です","url":"https://qiita.com/sugulu_Ogawa_ISID/items/439d106fc86f7f3724e7","tags":["Python","GitHub","機械学習","DeepLearning","githubcopilot"],"lgtm":6},{"username":"@marukome","avatar":"https://s3-ap-northeast-1.amazonaws.com/qiita-image-store/0/2599412/a5b4d1de08160d6df3035be893b6426f1446e4fa/x_large.png?1647345882","datetime":"2022-04-01T00:00:00Z","title":"rmで削除したファイルを復元できる lsof","url":"https://qiita.com/marukome/items/50f90f9a6f5078276e4d","tags":["SQL","lsof","rm"],"lgtm":13},{"username":"@Takao_","avatar":"https://qiita-image-store.s3.ap-northeast-1.amazonaws.com/0/438093/profile-images/1597560130","datetime":"2022-04-03T00:00:00Z","title":"アクセスログにクライアントIPが表示されていなかったので調査してみた。","url":"https://qiita.com/Takao_/items/cd593fa807099fd850bf","tags":["AWS","EC2","調査","Apache2.4"],"lgtm":4},{"username":"@degudegu2510(Qiita株式会社)","avatar":"https://qiita-image-store.s3.ap-northeast-1.amazonaws.com/0/390720/profile-images/1625041513","datetime":"2022-04-01T00:00:00Z","title":"【CSS】Gridレイアウトを使いこなすエンジニアはかっこいい！ ","url":"https://qiita.com/degudegu2510/items/8ef80cd811bf7d21c060","tags":["HTML","CSS","Design","デザイン","新人プログラマ応援"],"lgtm":18},{"username":"@torifukukaiou(fukuoka.ex (福岡Elixirコミュ))","avatar":"https://qiita-image-store.s3.ap-northeast-1.amazonaws.com/0/131808/profile-images/1616590306","datetime":"2022-04-03T00:00:00Z","title":"piyopiyo.ex #6：LiveViewでpiyopiyo.exの感想投稿サイトを作ろう！続き（2022/04/02）レポート","url":"https://qiita.com/torifukukaiou/items/3abaded3746c3d423a43","tags":["Elixir","Phoenix","AdventCalendar2022"],"lgtm":5},{"username":"@ishiayaya","avatar":"https://qiita-image-store.s3.ap-northeast-1.amazonaws.com/0/419691/profile-images/1569302030","datetime":"2022-04-02T00:00:00Z","title":"Intuneで検出されたアプリのPower BIの可視化","url":"https://qiita.com/ishiayaya/items/565f9bf4f278d589d4b7","tags":["GraphAPI","PowerBI","EMS","Intune"],"lgtm":9},{"username":"@toast-uz","avatar":"https://qiita-image-store.s3.amazonaws.com/0/156600/profile-images/1490109169","datetime":"2022-04-03T00:00:00Z","title":"Google Code Jam 2022 予選最終問題解説","url":"https://qiita.com/toast-uz/items/6a02f83b18b0102d1e1f","tags":["Python","アルゴリズム","競技プログラミング","GoogleCodeJam"],"lgtm":2},{"username":"@momoyamas","avatar":"https://secure.gravatar.com/avatar/e7f3b14f71ae1298021dc2aa86f4abc2","datetime":"2022-04-02T00:00:00Z","title":"TypescriptとReact 18の環境でcreateRootのエラー除去","url":"https://qiita.com/momoyamas/items/f9c4df46df0991160a26","tags":["TypeScript","React","React18"],"lgtm":2},{"username":"@Hashimoto-Noriaki","avatar":"https://s3-ap-northeast-1.amazonaws.com/qiita-image-store/0/1748789/b7483d00055fca0d6f915db8e1b10aaece026f7a/x_large.png?1636236981","datetime":"2022-04-01T00:00:00Z","title":"PHPの書き方(初心者向け)","url":"https://qiita.com/Hashimoto-Noriaki/items/3d89e79c1f031afc7b96","tags":["PHP","新人プログラマ応援"],"lgtm":4},{"username":"@nemutas","avatar":"https://s3-ap-northeast-1.amazonaws.com/qiita-image-store/0/358498/7ff8109ae23f5c613e6be245b484a69e3f2c1e75/x_large.png?1631787857","datetime":"2022-04-02T00:00:00Z","title":"Three.jsの勉強の仕方","url":"https://qiita.com/nemutas/items/d2d738749184a7a42f1d","tags":["three.js"],"lgtm":3},{"username":"@torifukukaiou(fukuoka.ex (福岡Elixirコミュ))","avatar":"https://qiita-image-store.s3.ap-northeast-1.amazonaws.com/0/131808/profile-images/1616590306","datetime":"2022-04-02T00:00:00Z","title":"【毎日自動更新】新人プログラマ応援 - みんなで新人を育てよう！（2022年04月） LGTMランキング！","url":"https://qiita.com/torifukukaiou/items/18dad64ba99aa5a40f95","tags":["Elixir","新人プログラマ応援","40代駆け出しエンジニア","AdventCalendar2022","Qiitadelika"],"lgtm":4},{"username":"@YuukiYoshida(株式会社Infreed)","avatar":"https://qiita-image-store.s3.amazonaws.com/0/354522/profile-images/1549243960","datetime":"2022-04-03T00:00:00Z","title":"【初心者応援】エンジニアにとって重要な2つのスキルとは？","url":"https://qiita.com/YuukiYoshida/items/94a50ff6437f1be2cc77","tags":["初心者向け","新人教育","新人プログラマ応援","初心者応援","エンジニアの心得"],"lgtm":2},{"username":"@st17086ts","avatar":"https://avatars.githubusercontent.com/u/49662655?v=4","datetime":"2022-04-03T00:00:00Z","title":"[Python]キーを入力するたびに音を鳴らすやつ（初投稿）","url":"https://qiita.com/st17086ts/items/c0f64f2327cdeeb8fcba","tags":["Python","初心者","#初投稿","#Keyboard"],"lgtm":2},{"username":"@e99h2121(株式会社Works Human Intelligence)","avatar":"https://s3-ap-northeast-1.amazonaws.com/qiita-image-store/0/93824/323a3ee1bb6f4a9fc03232a15b3c1203a23c1863/large.png?1612649035","datetime":"2022-04-02T00:00:00Z","title":"「Team Geek」を読み直したので、その要点","url":"https://qiita.com/e99h2121/items/d76e5a5bccc1c0498014","tags":["読書","TeamGeek"],"lgtm":1},{"username":"@paragraph14","avatar":"https://qiita-image-store.s3.ap-northeast-1.amazonaws.com/0/2597866/profile-images/1648313698","datetime":"2022-04-02T00:00:00Z","title":"AtCoder B,C問題をKotlinで解こう - ABC246","url":"https://qiita.com/paragraph14/items/c09495759b2fe17e94ba","tags":["Kotlin","AtCoder","初心者","競技プログラミング"],"lgtm":1},{"username":"@kaizen_nagoya","avatar":"https://qiita-image-store.s3.amazonaws.com/0/51423/profile-images/1535439333","datetime":"2022-04-03T00:00:00Z","title":"新人プログラマ応援　@kazuo_reve 新人の方によく展開している有益な情報（６）「できない人」ほど、人に聞けない","url":"https://qiita.com/kaizen_nagoya/items/a7417723b4b58d41614b","tags":["新人プログラマ応援","自分の頭で考える","AdventCalendar2022","Qiitadelika","みんなで新人を育てよう！"],"lgtm":1},{"username":"@Kiri8128","avatar":"https://secure.gravatar.com/avatar/67cb7d5616dcec2d6151103eb76a2fa5","datetime":"2022-04-01T00:00:00Z","title":"オンライン畳み込み","url":"https://qiita.com/Kiri8128/items/1738d5403764a0e26b4c","tags":["Python","algorithm","Python3","convolution"],"lgtm":2},{"username":"@oimasa","avatar":"https://secure.gravatar.com/avatar/72cf2e8da1effb4b34fe4273bd30dba6","datetime":"2022-04-01T00:00:00Z","title":"【Salesforce】メールアラートを使用して外部にメール送信する","url":"https://qiita.com/oimasa/items/bf9c8410246b7ced0f21","tags":["Salesforce","メールアラート"],"lgtm":1}]
